[{"categories":["documentation"],"content":"Documentos para baixar e iniciar a escrita da sua pesquisa.","date":"2020-03-06","objectID":"/documentos-importantes/","tags":["installation","configuration"],"title":"Documentos importantes!","uri":"/documentos-importantes/"},{"categories":["documentation"],"content":"Documentos importantes para baixar e iniciar a escrita da sua dissertação de mestrado. Site da pesquisa UNISA Neste link você encontra telefones úteis da direção de pesquisa da UNISA assim como documentos como o Formulário Pedido de Autorização para Realização de Projeto de Pesquisa Científica, toda a produção de pesquisa do programa, eventos científicos, informações sobre o biotério e laboratórios de pesquisa, entre outros! Comitê de Ética em Pesquisa - CEP Neste link tem informações fundamentais para que você entenda todos os passos para submissão do seu projeto ao comitê de ética tais como quais documentos devem ser apresentados, os modelos de documentos, orientações de como submeter. LEMBRE-SE ESSA ETAPA É FUNDAMENTAL PARA SEU PROJETO!! Normas ABNT Para acessar o Manual de Normatização de Trabalhos Acadêmicos clique aqui Modelo de dissertação Clique aqui para acessar um modelo de dissertação para você ir escrevendo seu documento dentro do modelo da UNISA.  ATENÇÃO!!! ISTO É UM MODELO, ENTÃO VOCÊ PRECISARÁ FAZER AJUSTES EM PARTICULAR NA SEÇÃO REVISÃO DE LITERATURA E NA METODOLOGIA!!! Solicitação de ficha catalográfica A solicitação da ficha catalográfica é a etapa final antes da entrega da dissertação. Para isso, você deverá fazer a solicitação através deste forms Enhancing the QUAlity and Transparency Of health Research - EQUATOR Clique neste Link para acessar as recomendações para apresentar sua pesquisa científica. Vale destacar que essas diretrizes são amplamente recomandadas e mundialmente utilizadas. ","date":"2020-03-06","objectID":"/documentos-importantes/:0:0","tags":["installation","configuration"],"title":"Documentos importantes!","uri":"/documentos-importantes/"},{"categories":null,"content":"About LoveIt","date":"2019-08-02","objectID":"/about/","tags":null,"title":"About LoveIt","uri":"/about/"},{"categories":null,"content":"  My First Paper é um site desenvolvido para ajudar você, meu aluno , a desenvolver sua dissertação de mestrado e seu primeiro artigo. Você encontrará neste site todas as informações necessárias para que você desenvolva sua dissertação, videos com orientações sobre como desenvolver cada seção, links para sites úteis, entre outros. TUDO EM UM MESMO LUGAR PARA FACILITAR O PROCESSO PARA VOCÊ Blog-dissertacaoHugo Theme LoveIt \" Blog-dissertacao Check the LICENSE file for details. ","date":"2019-08-02","objectID":"/about/:0:0","tags":null,"title":"About LoveIt","uri":"/about/"}]